odoo8_addon_business_requirement_etherpad-8.0.1.0.1-py2.7-nspkg.pth
odoo8_addon_business_requirement_etherpad-8.0.1.0.1.dist-info/DESCRIPTION.rst
odoo8_addon_business_requirement_etherpad-8.0.1.0.1.dist-info/METADATA
odoo8_addon_business_requirement_etherpad-8.0.1.0.1.dist-info/RECORD
odoo8_addon_business_requirement_etherpad-8.0.1.0.1.dist-info/WHEEL
odoo8_addon_business_requirement_etherpad-8.0.1.0.1.dist-info/metadata.json
odoo8_addon_business_requirement_etherpad-8.0.1.0.1.dist-info/namespace_packages.txt
odoo8_addon_business_requirement_etherpad-8.0.1.0.1.dist-info/top_level.txt
odoo_addons/business_requirement_etherpad/README.rst
odoo_addons/business_requirement_etherpad/__init__.py
odoo_addons/business_requirement_etherpad/__openerp__.py
odoo_addons/business_requirement_etherpad/data/pad_demo.xml
odoo_addons/business_requirement_etherpad/i18n/fr.po
odoo_addons/business_requirement_etherpad/i18n/sl.po
odoo_addons/business_requirement_etherpad/models/__init__.py
odoo_addons/business_requirement_etherpad/models/business.py
odoo_addons/business_requirement_etherpad/static/img/bus_etherpad.png
odoo_addons/business_requirement_etherpad/views/business_view.xml
